pyautogui_mcp/__init__.py
pyautogui_mcp/__main__.py
pyautogui_mcp/app.py
pyautogui_mcp-2026.1.101837.dist-info/licenses/LICENSE
pyautogui_mcp-2026.1.101837.dist-info/METADATA
pyautogui_mcp-2026.1.101837.dist-info/WHEEL
pyautogui_mcp-2026.1.101837.dist-info/entry_points.txt
pyautogui_mcp-2026.1.101837.dist-info/top_level.txt
pyautogui_mcp-2026.1.101837.dist-info/RECORD
