Metadata-Version: 2.4
Name: pyautogui-mcp
Version: 2026.1.101837
Summary: Expose PyAutoGUI through MCP.
Author-email: Eugene Evstafev <hi@eugene.plus>
License: BSD-3-Clause license
Project-URL: Repository, https://github.com/chigwell/pyautogui-mcp
Classifier: Programming Language :: Python :: 3.10
Classifier: Programming Language :: Python :: 3.11
Classifier: Programming Language :: Python :: 3.12
Classifier: License :: OSI Approved :: BSD License
Classifier: Operating System :: OS Independent
Requires-Python: >=3.10
License-File: LICENSE
Requires-Dist: anyio==4.12.0
Requires-Dist: fastmcp==2.14.2
Requires-Dist: pyautogui==0.9.54
Requires-Dist: pyscreeze==1.0.1
Requires-Dist: pillow>=10
Dynamic: license-file
